project1/zadatak2/top.vhd
library ieee;
use ieee.std_logic_1164.all;
use ieee.numeric_std.all;

entity top is
    port(
        fclk: in std_logic;
        insig: in std_logic;
        avrval: out unsigned (7 downto 0) := (others => '0')
       );
end top;


architecture arctop of top is
    begin
        main: process(fclk)
        variable last_state: std_logic :='0';
        variable length : integer := 0;
        variable count : integer := 0;
        variable result: integer range 1 to 100;
    
        begin
            if falling_edge(fclk) then
                length:=length+1;

                if insig = '1' then
                    count:=count+1;
                end if;

                if insig = '0' and last_state='1' then
                    result:=(count*100)/length;
                    count:= 0;
                    length:= 0;
                    avrval<=to_unsigned(result,8);
                end if;

                last_state:=insig;
            end if;
        end process;
            

end arctop;

project1/zadatak2/top_tb.vhd
library ieee;
use ieee.std_logic_1164.all;
use ieee.numeric_std.all;

entity top_tb is
end top_tb;

architecture arctop_tb of top_tb is

    component top is
      port (
        fclk: in std_logic;
        insig: in std_logic;
        avrval: out unsigned (7 downto 0) := (others => '0')
        );
    end component;


signal fclk: std_logic:='1';
signal insig: std_logic:='0';
signal avrval: unsigned (7 downto 0);


begin
	a: top port map (fclk=>fclk, insig=>insig, avrval=>avrval);

	clk: process
	
	begin
        assert false report "test began";
		fclk <= 'X';
		wait for 1 ns;
		
	
		for k in 0 to 200 loop
			fclk <= '0';
			wait for 1 ns;
			
			fclk <= '1';
			wait for 1 ns;	
		end loop;
			
		assert false report "test completed";
		wait;
		
	end process;

    avr: process
    begin
        insig <= '0';

        wait for 20 ns;
        insig <= '1';

        wait for 20 ns;
        insig <= '0';

        wait for 20 ns;
        insig <='1';

        wait for 60 ns;
        insig <= '0';

        wait for 10 ns;
        insig <='1';

        wait for 30 ns;
        insig <='0';

        wait for 20 ns;        

        wait;


    end process;

end arctop_tb;

project1/zadatak2/top.vcd
$date
  Fri May 26 16:18:37 2023
$end
$version
  GHDL v0
$end
$timescale
  1 fs
$end
$scope module standard $end
$upscope $end
$scope module std_logic_1164 $end
$upscope $end
$scope module numeric_std $end
$upscope $end
$scope module top_tb $end
$var reg 1 ! fclk $end
$var reg 1 " insig $end
$var reg 8 # avrval[7:0] $end
$scope module a $end
$var reg 1 $ fclk $end
$var reg 1 % insig $end
$var reg 8 & avrval[7:0] $end
$upscope $end
$upscope $end
$enddefinitions $end
#0
X!
0"
b00000000 #
X$
0%
b00000000 &
#1000000
0!
0$
#2000000
1!
1$
#3000000
0!
0$
#4000000
1!
1$
#5000000
0!
0$
#6000000
1!
1$
#7000000
0!
0$
#8000000
1!
1$
#9000000
0!
0$
#10000000
1!
1$
#11000000
0!
0$
#12000000
1!
1$
#13000000
0!
0$
#14000000
1!
1$
#15000000
0!
0$
#16000000
1!
1$
#17000000
0!
0$
#18000000
1!
1$
#19000000
0!
0$
#20000000
1!
1"
1$
1%
#21000000
0!
0$
#22000000
1!
1$
#23000000
0!
0$
#24000000
1!
1$
#25000000
0!
0$
#26000000
1!
1$
#27000000
0!
0$
#28000000
1!
1$
#29000000
0!
0$
#30000000
1!
1$
#31000000
0!
0$
#32000000
1!
1$
#33000000
0!
0$
#34000000
1!
1$
#35000000
0!
0$
#36000000
1!
1$
#37000000
0!
0$
#38000000
1!
1$
#39000000
0!
0$
#40000000
1!
0"
1$
0%
#41000000
0!
b00110010 #
0$
b00110010 &
#42000000
1!
1$
#43000000
0!
0$
#44000000
1!
1$
#45000000
0!
0$
#46000000
1!
1$
#47000000
0!
0$
#48000000
1!
1$
#49000000
0!
0$
#50000000
1!
1$
#51000000
0!
0$
#52000000
1!
1$
#53000000
0!
0$
#54000000
1!
1$
#55000000
0!
0$
#56000000
1!
1$
#57000000
0!
0$
#58000000
1!
1$
#59000000
0!
0$
#60000000
1!
1"
1$
1%
#61000000
0!
0$
#62000000
1!
1$
#63000000
0!
0$
#64000000
1!
1$
#65000000
0!
0$
#66000000
1!
1$
#67000000
0!
0$
#68000000
1!
1$
#69000000
0!
0$
#70000000
1!
1$
#71000000
0!
0$
#72000000
1!
1$
#73000000
0!
0$
#74000000
1!
1$
#75000000
0!
0$
#76000000
1!
1$
#77000000
0!
0$
#78000000
1!
1$
#79000000
0!
0$
#80000000
1!
1$
#81000000
0!
0$
#82000000
1!
1$
#83000000
0!
0$
#84000000
1!
1$
#85000000
0!
0$
#86000000
1!
1$
#87000000
0!
0$
#88000000
1!
1$
#89000000
0!
0$
#90000000
1!
1$
#91000000
0!
0$
#92000000
1!
1$
#93000000
0!
0$
#94000000
1!
1$
#95000000
0!
0$
#96000000
1!
1$
#97000000
0!
0$
#98000000
1!
1$
#99000000
0!
0$
#100000000
1!
1$
#101000000
0!
0$
#102000000
1!
1$
#103000000
0!
0$
#104000000
1!
1$
#105000000
0!
0$
#106000000
1!
1$
#107000000
0!
0$
#108000000
1!
1$
#109000000
0!
0$
#110000000
1!
1$
#111000000
0!
0$
#112000000
1!
1$
#113000000
0!
0$
#114000000
1!
1$
#115000000
0!
0$
#116000000
1!
1$
#117000000
0!
0$
#118000000
1!
1$
#119000000
0!
0$
#120000000
1!
0"
1$
0%
#121000000
0!
b01001011 #
0$
b01001011 &
#122000000
1!
1$
#123000000
0!
0$
#124000000
1!
1$
#125000000
0!
0$
#126000000
1!
1$
#127000000
0!
0$
#128000000
1!
1$
#129000000
0!
0$
#130000000
1!
1"
1$
1%
#131000000
0!
0$
#132000000
1!
1$
#133000000
0!
0$
#134000000
1!
1$
#135000000
0!
0$
#136000000
1!
1$
#137000000
0!
0$
#138000000
1!
1$
#139000000
0!
0$
#140000000
1!
1$
#141000000
0!
0$
#142000000
1!
1$
#143000000
0!
0$
#144000000
1!
1$
#145000000
0!
0$
#146000000
1!
1$
#147000000
0!
0$
#148000000
1!
1$
#149000000
0!
0$
#150000000
1!
1$
#151000000
0!
0$
#152000000
1!
1$
#153000000
0!
0$
#154000000
1!
1$
#155000000
0!
0$
#156000000
1!
1$
#157000000
0!
0$
#158000000
1!
1$
#159000000
0!
0$
#160000000
1!
0"
1$
0%
