project1/zadatak3/top.vhd
library ieee;
use ieee.std_logic_1164.all;
use ieee.numeric_std.all;

--mc out

entity top is
    port(
        fclk: in std_logic;
        oneh: in unsigned (7 downto 0) := (others => '0');
        onel: in unsigned (7 downto 0) := (others => '0');
        onesubper: in unsigned (7 downto 0) := (others => '0');
        zeroh: in unsigned (7 downto 0) := (others => '0');
        zerol: in unsigned (7 downto 0) := (others => '0');
        zerosubper: in unsigned (7 downto 0) := (others => '0');
        sigval: in std_logic_vector (7 downto 0) := (others => '0');
        mi: in std_logic;
        mc: out std_logic:='0';
        modsig: out std_logic:='0'
       );
end top;


architecture arctop of top is

    begin
        main: process(fclk)
        variable ctr: unsigned (7 downto 0):= "00000000";
        variable ctrh: unsigned (7 downto 0):= "00000000";
        variable ctrl: unsigned (7 downto 0):= "00000000";
        variable ctrsub: unsigned (7 downto 0):= "00000000";
        variable idx: integer:=7;

        begin
            
            if falling_edge(fclk) then
                if rising_edge(mi) then
                    mc<='0';
                end if;

                if falling_edge(mi) then
                    mc<='1';
                    ctr:="00000000";
                    ctrh:="00000000";
                    ctrl:="00000000";
                    ctrsub:="00000000";
                    idx:=0;
                end if;

                if mi='1' then

                    if idx>-1 then

                    if sigval(idx)='1' then
                        ctr:=ctr+1;
                        
                        if ctr<=onel then
                            modsig<='0';
                            last_state:='0';
                        end if;

                        if ctr>onel and ctr<=(onel+oneh) then

                            if ctrsub<(onesubper/2) then
                                modsig<='0';
                                ctrsub:=ctrsub+1;
                            elsif ctrsub>=(onesubper/2) and ctrsub<onesubper-1 then
                                modsig<='1';
                                ctrsub:=ctrsub+1;
                            elsif ctrsub>=onesubper-1 then
                                ctrsub:="00000000";
                            end if;
                        end if;

                        if ctr>(onel+oneh) then
                            ctr:="00000000";
                            ctrh:="00000000";
                            ctrl:="00000000";
                            ctrsub:="00000000";
                            idx:=idx-1;
                        end if;

                    else

                        ctr:=ctr+1;

                        if ctr<=zeroh then

                            if ctrsub<=(zerosubper/2) then
                                modsig<='0';
                                ctrsub:=ctrsub+1;
                            end if;

                            if ctrsub>(zerosubper/2) and ctrsub<=zerosubper then
                                modsig<='1';
                                ctrsub:=ctrsub+1;
                            end if;

                            if ctrsub=zerosubper+1 then
                                ctrsub:="00000000";
                            end if;

                        end if;

                        if ctr>zeroh and ctr<=zeroh+zerol then

                            modsig<='0';

                        end if;

                        if ctr=zeroh+zerol then
                            ctr:="00000000";
                            ctrh:="00000000";
                            ctrl:="00000000";
                            ctrsub:="00000000";
                            idx:=idx-1;
                        end if;
                    end if;

                        if idx<0 then
                            idx:=7;
                            modsig<='0';
                        end if;

                    end if;

                end if;
            end if;
        end process;
end arctop;

project1/zadatak3/top_tb.vhd
library ieee;
use ieee.std_logic_1164.all;
use ieee.numeric_std.all;

entity top_tb is
end top_tb;

architecture arctop_tb of top_tb is
component top 
    port(
    oneh : in unsigned(7 downto 0);
    onel : in unsigned(7 downto 0);
    onesubper : in unsigned(7 downto 0);
    zeroh : in unsigned(7 downto 0);
    zerol : in unsigned(7 downto 0);
    zerosubper : in unsigned(7 downto 0);
    mi : in std_logic;
    mc : out std_logic := '0';
    sigval : in std_logic_vector(7 downto 0);
    modsig : out std_logic:= '0';
    fclk: in std_logic:='0'
    );
end component;

signal oneh :  unsigned(7 downto 0) := x"32";
signal onel :  unsigned(7 downto 0) := x"64";
signal onesubper : unsigned(7 downto 0):= x"0A";
signal zeroh : unsigned(7 downto 0):= x"1E";
signal zerol : unsigned(7 downto 0):= x"5A";
signal zerosubper :  unsigned(7 downto 0):= x"0A";
signal mi : std_logic := '0';
signal mc : std_logic := '0';
signal sigval :  std_logic_vector(7 downto 0) := x"00";
signal modsig :  std_logic:= '0';
signal fclk: std_logic :='0';

begin 
    main: top port map(fclk => fclk, modsig => modsig, sigval => sigval, mc => mc, mi => mi, zerosubper => zerosubper, zerol => zerol, zeroh => zeroh, onesubper => onesubper, onel => onel, oneh => oneh);

    process
    begin
        fclk <= '0'; 

        sigval <= x"DE"; 
        mi <= '1';
        for i in 0 to 1200 loop
            wait for 0.5 ns;
            fclk <= '1';
            wait for 0.5 ns;
            fclk <= '0';
        end loop;
        mi<='0';
        for i in 0 to 50 loop
            wait for 0.5 ns;
            fclk <= '1';
            wait for 0.5 ns;
            fclk <= '0';
        end loop;

        sigval <= x"AD";
        mi<='1';
        for k in 0 to 1200 loop
            wait for 0.5 ns;
            fclk <= '1';
            wait for 0.5 ns;
            fclk <= '0';
        end loop;
        mi<='0';

        for i in 0 to 50 loop
            wait for 0.5 ns;
            fclk <= '1';
            wait for 0.5 ns;
            fclk <= '0';
        end loop;
        sigval <= x"BE";
        mi<='1';
        for i in 0 to 1200 loop
            wait for 0.5 ns;
            fclk <= '1';
            wait for 0.5 ns;
            fclk <= '0';
        end loop;
        mi<='0';

        for i in 0 to 50 loop
            wait for 0.5 ns;
            fclk <= '1';
            wait for 0.5 ns;
            fclk <= '0';
        end loop;
        sigval <= x"EF";
        mi<='1';
        for i in 0 to 1200 loop
            wait for 0.5 ns;
            fclk <= '1';
            wait for 0.5 ns;
            fclk <= '0';
        end loop;
        mi<='0';
        
        for i in 0 to 1200 loop
            wait for 0.5 ns;
            fclk <= '1';
            wait for 0.5 ns;
            fclk <= '0';
        end loop;

		wait;
		
	end process;
end arctop_tb;

project1/zadatak3/top.vcd
$date
  Sat May 27 14:25:30 2023
$end
$version
  GHDL v0
$end
$timescale
  1 fs
$end
$scope module standard $end
$upscope $end
$scope module std_logic_1164 $end
$upscope $end
$scope module numeric_std $end
$upscope $end
$scope module top_tb $end
$var reg 8 ! oneh[7:0] $end
$var reg 8 " onel[7:0] $end
$var reg 8 # onesubper[7:0] $end
$var reg 8 $ zeroh[7:0] $end
$var reg 8 % zerol[7:0] $end
$var reg 8 & zerosubper[7:0] $end
$var reg 1 ' mi $end
$var reg 1 ( mc $end
$var reg 8 ) sigval[7:0] $end
$var reg 1 * modsig $end
$var reg 1 + fclk $end
$scope module main $end
$var reg 1 , fclk $end
$var reg 8 - oneh[7:0] $end
$var reg 8 . onel[7:0] $end
$var reg 8 / onesubper[7:0] $end
$var reg 8 0 zeroh[7:0] $end
$var reg 8 1 zerol[7:0] $end
$var reg 8 2 zerosubper[7:0] $end
$var reg 8 3 sigval[7:0] $end
$var reg 1 4 mi $end
$var reg 1 5 mc $end
$var reg 1 6 modsig $end
$upscope $end
$upscope $end
$enddefinitions $end
#0
b00110010 !
b01100100 "
b00001010 #
b00011110 $
b01011010 %
b00001010 &
1'
0(
b11011110 )
0*
0+
0,
b00110010 -
b01100100 .
b00001010 /
b00011110 0
b01011010 1
b00001010 2
b11011110 3
14
05
06
#500000
1+
1,
#1000000
0+
0,
#1500000
1+
1,
#2000000
0+
0,
#2500000
1+
1,
#3000000
0+
0,
#3500000
1+
1,
#4000000
0+
0,
#4500000
1+
1,
#5000000
0+
0,
#5500000
1+
1,
#6000000
0+
0,
#6500000
1+
1,
#7000000
0+
0,
#7500000
1+
1,
#8000000
0+
0,
#8500000
1+
1,
#9000000
0+
0,
#9500000
1+
1,
#10000000
0+
0,
#10500000
1+
1,
#11000000
0+
0,
#11500000
1+
1,
#12000000
0+
0,
#12500000
1+
1,
#13000000
0+
0,
#13500000
1+
1,
#14000000
0+
0,
#14500000
1+
1,
#15000000
0+
0,
#15500000
1+
1,
#16000000
0+
0,
#16500000
1+
1,
#17000000
0+
0,
#17500000
1+
1,
#18000000
0+
0,
#18500000
1+
1,
#19000000
0+
0,
#19500000
1+
1,
#20000000
0+
0,
#20500000
1+
1,
#21000000
0+
0,
#21500000
1+
1,
#22000000
0+
0,
#22500000
1+
1,
#23000000
0+
0,
#23500000
1+
1,
#24000000
0+
0,
#24500000
1+
1,
#25000000
0+
0,
#25500000
1+
1,
#26000000
0+
0,
#26500000
1+
1,
#27000000
0+
0,
#27500000
1+
1,
#28000000
0+
0,
#28500000
1+
1,
#29000000
0+
0,
#29500000
1+
1,
#30000000
0+
0,
#30500000
1+
1,
#31000000
0+
0,
#31500000
1+
1,
#32000000
0+
0,
#32500000
1+
1,
#33000000
0+
0,
#33500000
1+
1,
#34000000
0+
0,
#34500000
1+
1,
#35000000
0+
0,
#35500000
1+
1,
#36000000
0+
0,
#36500000
1+
1,
#37000000
0+
0,
#37500000
1+
1,
#38000000
0+
0,
#38500000
1+
1,
#39000000
0+
0,
#39500000
1+
1,
#40000000
0+
0,
#40500000
1+
1,
#41000000
0+
0,
#41500000
1+
1,
#42000000
0+
0,
#42500000
1+
1,
#43000000
0+
0,
#43500000
1+
1,
#44000000
0+
0,
#44500000
1+
1,
#45000000
0+
0,
#45500000
1+
1,
#46000000
0+
0,
#46500000
1+
1,
#47000000
0+
0,
#47500000
1+
1,
#48000000
0+
0,
#48500000
1+
1,
#49000000
0+
0,
#49500000
1+
1,
#50000000
0+
0,
#50500000
1+
1,
#51000000
0+
0,
#51500000
1+
1,
#52000000
0+
0,
#52500000
1+
1,
#53000000
0+
0,
#53500000
1+
1,
#54000000
0+
0,
#54500000
1+
1,
#55000000
0+
0,
#55500000
1+
1,
#56000000
0+
0,
#56500000
1+
1,
#57000000
0+
0,
#57500000
1+
1,
#58000000
0+
0,
#58500000
1+
1,
#59000000
0+
0,
#59500000
1+
1,
#60000000
0+
0,
#60500000
1+
1,
#61000000
0+
0,
#61500000
1+
1,
#62000000
0+
0,
#62500000
1+
1,
#63000000
0+
0,
#63500000
1+
1,
#64000000
0+
0,
#64500000
1+
1,
#65000000
0+
0,
#65500000
1+
1,
#66000000
0+
0,
#66500000
1+
1,
#67000000
0+
0,
#67500000
1+
1,
#68000000
0+
0,
#68500000
1+
1,
#69000000
0+
0,
#69500000
1+
1,
#70000000
0+
0,
#70500000
1+
1,
#71000000
0+
0,
#71500000
1+
1,
#72000000
0+
0,
#72500000
1+
1,
#73000000
0+
0,
#73500000
1+
1,
#74000000
0+
0,
#74500000
1+
1,
#75000000
0+
0,
#75500000
1+
1,
#76000000
0+
0,
#76500000
1+
1,
#77000000
0+
0,
#77500000
1+
1,
#78000000
0+
0,
#78500000
1+
1,
#79000000
0+
0,
#79500000
1+
1,
#80000000
0+
0,
#80500000
1+
1,
#81000000
0+
0,
#81500000
1+
1,
#82000000
0+
0,
#82500000
1+
1,
#83000000
0+
0,
#83500000
1+
1,
#84000000
0+
0,
#84500000
1+
1,
#85000000
0+
0,
#85500000
1+
1,
#86000000
0+
0,
#86500000
1+
1,
#87000000
0+
0,
#87500000
1+
1,
#88000000
0+
0,
#88500000
1+
1,
#89000000
0+
0,
#89500000
1+
1,
#90000000
0+
0,
#90500000
1+
1,
#91000000
0+
0,
#91500000
1+
1,
#92000000
0+
0,
#92500000
1+
1,
#93000000
0+
0,
#93500000
1+
1,
#94000000
0+
0,
#94500000
1+
1,
#95000000
0+
0,
#95500000
1+
1,
#96000000
0+
0,
#96500000
1+
1,
#97000000
0+
0,
#97500000
1+
1,
#98000000
0+
0,
#98500000
1+
1,
#99000000
0+
0,
#99500000
1+
1,
#100000000
0+
0,
#100500000
1+
1,
#101000000
0+
0,
#101500000
1+
1,
#102000000
0+
0,
#102500000
1+
1,
#103000000
0+
0,
#103500000
1+
1,
#104000000
0+
0,
#104500000
1+
1,
#105000000
0+
0,
#105500000
1+
1,
#106000000
1*
0+
0,
16
#106500000
1+
1,
#107000000
0+
0,
#107500000
1+
1,
#108000000
0+
0,
#108500000
1+
1,
#109000000
0+
0,
#109500000
1+
1,
#110000000
0+
0,
#110500000
1+
1,
#111000000
0*
0+
0,
06
#111500000
1+
1,
#112000000
0+
0,
#112500000
1+
1,
#113000000
0+
0,
#113500000
1+
1,
#114000000
0+
0,
#114500000
1+
1,
#115000000
0+
0,
#115500000
1+
1,
#116000000
1*
0+
0,
16
#116500000
1+
1,
#117000000
0+
0,
#117500000
1+
1,
#118000000
0+
0,
#118500000
1+
1,
#119000000
0+
0,
#119500000
1+
1,
#120000000
0+
0,
#120500000
1+
1,
#121000000
0*
0+
0,
06
#121500000
1+
1,
#122000000
0+
0,
#122500000
1+
1,
#123000000
0+
0,
#123500000
1+
1,
#124000000
0+
0,
#124500000
1+
1,
#125000000
0+
0,
#125500000
1+
1,
#126000000
1*
0+
0,
16
#126500000
1+
1,
#127000000
0+
0,
#127500000
1+
1,
#128000000
0+
0,
#128500000
1+
1,
#129000000
0+
0,
#129500000
1+
1,
#130000000
0+
0,
#130500000
1+
1,
#131000000
0*
0+
0,
06
#131500000
1+
1,
#132000000
0+
0,
#132500000
1+
1,
#133000000
0+
0,
#133500000
1+
1,
#134000000
0+
0,
#134500000
1+
1,
#135000000
0+
0,
#135500000
1+
1,
#136000000
1*
0+
0,
16
#136500000
1+
1,
#137000000
0+
0,
#137500000
1+
1,
#138000000
0+
0,
#138500000
1+
1,
#139000000
0+
0,
#139500000
1+
1,
#140000000
0+
0,
#140500000
1+
1,
#141000000
0*
0+
0,
06
#141500000
1+
1,
#142000000
0+
0,
#142500000
1+
1,
#143000000
0+
0,
#143500000
1+
1,
#144000000
0+
0,
#144500000
1+
1,
#145000000
0+
0,
#145500000
1+
1,
#146000000
1*
0+
0,
16
#146500000
1+
1,
#147000000
0+
0,
#147500000
1+
1,
#148000000
0+
0,
#148500000
1+
1,
#149000000
0+
0,
#149500000
1+
1,
#150000000
0+
0,
#150500000
1+
1,
#151000000
0+
0,
#151500000
1+
1,
#152000000
0*
0+
0,
06
